simple_value_object/__init__.py
simple_value_object/decorators.py
simple_value_object/exceptions.py
simple_value_object/value_object.py
simple_value_object-1.5.dist-info/AUTHORS
simple_value_object-1.5.dist-info/LICENSE
simple_value_object-1.5.dist-info/METADATA
simple_value_object-1.5.dist-info/WHEEL
simple_value_object-1.5.dist-info/top_level.txt
simple_value_object-1.5.dist-info/RECORD
