Metadata-Version: 2.1
Name: simple-value-object
Version: 1.5
Summary: A simple mixin for create Value Objects
Home-page: https://github.com/quiqueporta/value-object
Author: Quique Porta
Author-email: quiqueporta@gmail.com
License: MIT/X11
Download-URL: https://github.com/quiqueporta/simple-value-object/releases
Keywords: python,ddd
Platform: UNKNOWN
Classifier: Development Status :: 5 - Production/Stable
Classifier: Intended Audience :: Developers
Classifier: License :: OSI Approved :: MIT License
Classifier: Natural Language :: English
Classifier: Operating System :: OS Independent
Classifier: Programming Language :: Python
Classifier: Topic :: Utilities
